omniregress-4.1.1.dist-info/METADATA
omniregress-4.1.1.dist-info/WHEEL
omniregress-4.1.1.dist-info/licenses/LICENSE
omniregress/__init__.py
omniregress/_omniregress.cp39-win_amd64.pyd
omniregress/lasso_regression.py
omniregress/linear_regression.py
omniregress/logistic_regression.py
omniregress/polynomial_regression.py
omniregress/ridge_regression.py
omniregress-4.1.1.dist-info/RECORD
